README.md
setup.py
shadpy/__init__.py
shadpy/client.py
shadpy/exceptions.py
shadpy/filters.py
shadpy/handlers.py
shadpy/network.py
shadpy/sync.py
shadpy/utils.py
shadpy.egg-info/PKG-INFO
shadpy.egg-info/SOURCES.txt
shadpy.egg-info/dependency_links.txt
shadpy.egg-info/requires.txt
shadpy.egg-info/top_level.txt
shadpy/bots/__init__.py
shadpy/bots/client.py
shadpy/bots/types/__init__.py
shadpy/bots/types/aux_data.py
shadpy/bots/types/bot.py
shadpy/bots/types/bot_command.py
shadpy/bots/types/button.py
shadpy/bots/types/button_calendar.py
shadpy/bots/types/button_location.py
shadpy/bots/types/button_number_picker.py
shadpy/bots/types/button_selection.py
shadpy/bots/types/button_selection_item.py
shadpy/bots/types/button_string_picker.py
shadpy/bots/types/button_textbox.py
shadpy/bots/types/chat.py
shadpy/bots/types/contact_message.py
shadpy/bots/types/file.py
shadpy/bots/types/forwarded_from.py
shadpy/bots/types/inline_message.py
shadpy/bots/types/keypad.py
shadpy/bots/types/keypad_row.py
shadpy/bots/types/live_location.py
shadpy/bots/types/location.py
shadpy/bots/types/messaage_text_update.py
shadpy/bots/types/message.py
shadpy/bots/types/message_keypad_update.py
shadpy/bots/types/payment_status.py
shadpy/bots/types/poll.py
shadpy/bots/types/poll_status.py
shadpy/bots/types/sticker.py
shadpy/bots/types/update.py
shadpy/crypto/__init__.py
shadpy/crypto/crypto.py
shadpy/enums/__init__.py
shadpy/enums/chat_access_type.py
shadpy/enums/chat_action.py
shadpy/enums/chat_type.py
shadpy/enums/message_media_type.py
shadpy/enums/parse_mode.py
shadpy/enums/poll_type.py
shadpy/enums/reaction_type.py
shadpy/enums/report_type.py
shadpy/methods/__init__.py
shadpy/methods/advanced/__init__.py
shadpy/methods/advanced/build.py
shadpy/methods/auth/__init__.py
shadpy/methods/auth/register_device.py
shadpy/methods/auth/send_code.py
shadpy/methods/auth/sign_in.py
shadpy/methods/channels/__init__.py
shadpy/methods/channels/add_channel.py
shadpy/methods/channels/add_channel_members.py
shadpy/methods/channels/ban_channel_member.py
shadpy/methods/channels/channel_preview_by_join_link.py
shadpy/methods/channels/check_channel_username.py
